mmm_fair_cli/__init__.py
mmm_fair_cli/data_process.py
mmm_fair_cli/dataset.py
mmm_fair_cli/dataset_visualization.py
mmm_fair_cli/deploy_utils.py
mmm_fair_cli/fairlearn_report.py
mmm_fair_cli/hyperparams.py
mmm_fair_cli/mammoth_csv.py
mmm_fair_cli/mmm_fair.py
mmm_fair_cli/mmm_fair_gb.py
mmm_fair_cli/onnx_utils.py
mmm_fair_cli/train_and_deploy.py
mmm_fair_cli/viz_trade_offs.py
mmm_fair_cli-1.1.1.dist-info/licenses/LICENSE
mmm_fair_cli-1.1.1.dist-info/METADATA
mmm_fair_cli-1.1.1.dist-info/WHEEL
mmm_fair_cli-1.1.1.dist-info/entry_points.txt
mmm_fair_cli-1.1.1.dist-info/top_level.txt
mmm_fair_cli-1.1.1.dist-info/RECORD
