Metadata-Version: 2.4
Name: mmm-fair-cli
Version: 1.1.1
Summary: CLI-only version of the MMM-Fair boosting classifier
Author-email: Arjun Roy <arjunroyihrpa@gmail.com>, Swati Swati <swati17293@gmail.com>, Emmanouil Panagiotou <panagiotouemm@gmail.com>
License:                                  Apache License
Project-URL: Homepage, https://github.com/arjunroyihrpa/MMM_fair
Project-URL: Bug Tracker, https://github.com/arjunroyihrpa/MMM_fair/issues
Keywords: fairness,boosting,classification,machine-learning,cli
Requires-Python: >=3.12
License-File: LICENSE
Requires-Dist: numpy>=1.26.4
Requires-Dist: six>=1.16.0
Requires-Dist: pymoo>=0.6.1.3
Requires-Dist: scikit-learn>=1.5.2
Requires-Dist: ucimlrepo
Requires-Dist: pandas>=2.2.3
Requires-Dist: fairbench
Requires-Dist: skl2onnx
Requires-Dist: tqdm
Requires-Dist: onnxruntime
Requires-Dist: fairlearn
Requires-Dist: rich
Requires-Dist: plotly
Dynamic: license-file
